pythia/Pythia.py
pythia/__init__.py
pythia/test.py
pythia/agents/__init__.py
pythia/agents/sensitivity.py
pythia/agents/specialist.py
pythia/agents/specificity.py
pythia/core/__init__.py
pythia/core/agentic_workflow.py
pythia/core/split.py
pythia/core/validation_workflow.py
pythia/llm/__init__.py
pythia/llm/base.py
pythia/llm/pythia_gemini.py
pythia/llm/pythia_ollama.py
pythia/llm/pythia_openai.py
pythia/utility/__init__.py
pythia/utility/evaluation.py
pythia/utility/localLLM.py
pythia/utility/utils.py
pythia_tool-1.0.2.dist-info/LICENSE
pythia_tool-1.0.2.dist-info/METADATA
pythia_tool-1.0.2.dist-info/WHEEL
pythia_tool-1.0.2.dist-info/top_level.txt
pythia_tool-1.0.2.dist-info/RECORD
