Metadata-Version: 2.1
Name: pythia_tool
Version: 1.0.2
Summary: An LLM driven prompt improvement tool for optimizing LLM applications.
Home-page: https://github.com/clai-group/Pythia
Author: Cameron Cagan
Author-email: ccagan@mgh.harvard.edu
License: MIT
Project-URL: Documentation, https://github.com/clai-group/Pythia/blob/main/README.md
Project-URL: Source, https://github.com/clai-group/Pythia
Project-URL: Tracker, https://github.com/clai-group/Pythia/issues
Keywords: llm prompt improvement ai iterative optimization
Classifier: Development Status :: 3 - Alpha
Classifier: Intended Audience :: Developers
Classifier: Intended Audience :: Science/Research
Classifier: License :: OSI Approved :: MIT License
Classifier: Operating System :: OS Independent
Classifier: Programming Language :: Python :: 3
Classifier: Programming Language :: Python :: 3.9
Classifier: Programming Language :: Python :: 3.10
Classifier: Programming Language :: Python :: 3.11
Classifier: Programming Language :: Python :: 3.12
Classifier: Topic :: Scientific/Engineering :: Artificial Intelligence
Classifier: Topic :: Software Development :: Libraries :: Python Modules
Requires-Python: >=3.9
License-File: LICENSE
Requires-Dist: langchain-core >=0.1.3
Requires-Dist: openai >=2.9.0
Requires-Dist: pandas >=2.3.3
Requires-Dist: scikit-learn >=1.7.2
Requires-Dist: httpx >=0.28.1
Provides-Extra: google
Requires-Dist: google-auth ; extra == 'google'
Requires-Dist: google-genai ; extra == 'google'
Provides-Extra: ollama
Requires-Dist: ollama ; extra == 'ollama'
Provides-Extra: openai
Requires-Dist: openai ; extra == 'openai'
